{
  "entries" : [
    {
      "name" : "Moya",
      "url" : "https:\/\/github.com\/Moya\/Moya"
    },
    {
      "name" : "Marathon",
      "url" : "https:\/\/github.com\/JohnSundell\/Marathon"
    },
    {
      "name" : "M13Checkbox",
      "url" : "https:\/\/github.com\/Marxon13\/M13Checkbox"
    },
    {
      "name" : "mapper",
      "url" : "https:\/\/github.com\/lyft\/mapper"
    },
    {
      "name" : "Metron",
      "url" : "https:\/\/github.com\/toineheuvelmans\/Metron"
    },
    {
      "name" : "Magnetic",
      "url" : "https:\/\/github.com\/efremidze\/Magnetic"
    },
    {
      "name" : "Marshal",
      "url" : "https:\/\/github.com\/utahiosmac\/Marshal"
    },
    {
      "name" : "ModelRocket",
      "url" : "https:\/\/github.com\/ovenbits\/ModelRocket"
    }
  ]
}